odoo/addons/account_payment_partner/README.rst
odoo/addons/account_payment_partner/__init__.py
odoo/addons/account_payment_partner/__manifest__.py
odoo/addons/account_payment_partner/demo/partner_demo.xml
odoo/addons/account_payment_partner/i18n/account_payment_partner.pot
odoo/addons/account_payment_partner/i18n/ca.po
odoo/addons/account_payment_partner/i18n/da_DK.po
odoo/addons/account_payment_partner/i18n/de.po
odoo/addons/account_payment_partner/i18n/es.po
odoo/addons/account_payment_partner/i18n/es_AR.po
odoo/addons/account_payment_partner/i18n/fr.po
odoo/addons/account_payment_partner/i18n/hr.po
odoo/addons/account_payment_partner/i18n/nb_NO.po
odoo/addons/account_payment_partner/i18n/nl.po
odoo/addons/account_payment_partner/i18n/pt_BR.po
odoo/addons/account_payment_partner/i18n/sl.po
odoo/addons/account_payment_partner/migrations/13.0.1.0.0/post-migration.py
odoo/addons/account_payment_partner/migrations/13.0.1.0.0/pre-migration.py
odoo/addons/account_payment_partner/models/__init__.py
odoo/addons/account_payment_partner/models/account_move.py
odoo/addons/account_payment_partner/models/account_move_line.py
odoo/addons/account_payment_partner/models/account_payment_mode.py
odoo/addons/account_payment_partner/models/res_partner.py
odoo/addons/account_payment_partner/readme/CONTRIBUTORS.rst
odoo/addons/account_payment_partner/readme/DESCRIPTION.rst
odoo/addons/account_payment_partner/readme/HISTORY.rst
odoo/addons/account_payment_partner/readme/USAGE.rst
odoo/addons/account_payment_partner/reports/__init__.py
odoo/addons/account_payment_partner/reports/account_invoice_report.py
odoo/addons/account_payment_partner/reports/account_invoice_report_view.xml
odoo/addons/account_payment_partner/static/description/icon.png
odoo/addons/account_payment_partner/static/description/index.html
odoo/addons/account_payment_partner/tests/__init__.py
odoo/addons/account_payment_partner/tests/test_account_payment_partner.py
odoo13_addon_account_payment_partner-13.0.1.5.0.dist-info/METADATA
odoo13_addon_account_payment_partner-13.0.1.5.0.dist-info/WHEEL
odoo13_addon_account_payment_partner-13.0.1.5.0.dist-info/top_level.txt
odoo13_addon_account_payment_partner-13.0.1.5.0.dist-info/RECORD
