Metadata-Version: 2.1
Name: odoo13-addon-account-payment-partner
Version: 13.0.1.5.0
Summary: Adds payment mode on partners and invoices
Home-page: https://github.com/OCA/bank-payment
Author: Akretion, Tecnativa, Odoo Community Association (OCA)
Author-email: support@odoo-community.org
License: AGPL-3
Platform: UNKNOWN
Classifier: Programming Language :: Python
Classifier: Framework :: Odoo
Classifier: Framework :: Odoo :: 13.0
Classifier: License :: OSI Approved :: GNU Affero General Public License v3
Classifier: Development Status :: 6 - Mature
Requires-Python: >=3.5
Requires-Dist: odoo13-addon-account-payment-mode
Requires-Dist: odoo (<13.1dev,>=13.0a)
